SimplyEDA.py
SimplyEDA-0.1.7.dist-info/LICENSE
SimplyEDA-0.1.7.dist-info/METADATA
SimplyEDA-0.1.7.dist-info/WHEEL
SimplyEDA-0.1.7.dist-info/top_level.txt
SimplyEDA-0.1.7.dist-info/RECORD
