Metadata-Version: 2.1
Name: SimplyEDA
Version: 0.1.7
Summary: A simple library for exploratory data analysis
Home-page: https://github.com/kitranet/SimpleEDA
Author: M.R.Vijay Krishnan
Author-email: vijaykrishnanmr@gmail.com
Keywords: EDA data-analysis
Classifier: Programming Language :: Python :: 3
Classifier: License :: OSI Approved :: MIT License
Classifier: Operating System :: OS Independent
Requires-Python: >=3.6
License-File: LICENSE
Requires-Dist: seaborn
Requires-Dist: matplotlib
Requires-Dist: numpy
Requires-Dist: pandas
Requires-Dist: statsmodels
